README.md
setup.py
SQLAlchemy_One.egg-info/PKG-INFO
SQLAlchemy_One.egg-info/SOURCES.txt
SQLAlchemy_One.egg-info/dependency_links.txt
SQLAlchemy_One.egg-info/not-zip-safe
SQLAlchemy_One.egg-info/requires.txt
SQLAlchemy_One.egg-info/top_level.txt
example/__init__.py
example/app.py
sqlalchemy_plus/__init__.py
sqlalchemy_plus/dao.py
sqlalchemy_plus/database.py
sqlalchemy_plus/helpers.py
sqlalchemy_plus/processor.py
sqlalchemy_plus/transformer.py
sqlalchemy_plus/types.py
sqlalchemy_plus/mixins/__init__.py
sqlalchemy_plus/mixins/abstracts.py
sqlalchemy_plus/mixins/columns.py
sqlalchemy_plus/mixins/core.py
sqlalchemy_plus/query/__init__.py
sqlalchemy_plus/query/buffer.py
sqlalchemy_plus/query/processor.py