Metadata-Version: 2.1
Name: SQLAlchemy-One
Version: 0.0.2
Summary: Helpers package for SQL-Alchemy
Home-page: https://github.com/kmjbyrne/sqlalchemy-one
Author: Keith Byrne
Author-email: keithmbyrne@gmail.com
License: MIT
Keywords: python library utilities
Platform: UNKNOWN
Classifier: Development Status :: 3 - Alpha
Classifier: License :: OSI Approved :: MIT License
Classifier: Programming Language :: Python :: 3.7
